deeply_learnable_package/__init__.py
deeply_learnable_package/classification.py
deeply_learnable_package/images.py
deeply_learnable_package/regression.py
deeply_learnable_package-0.1.4.dist-info/METADATA
deeply_learnable_package-0.1.4.dist-info/WHEEL
deeply_learnable_package-0.1.4.dist-info/top_level.txt
deeply_learnable_package-0.1.4.dist-info/RECORD
